vaccines/__init__.py
vaccines/the.proc.py
vaccines/_coms/clique_pro/__init__.py
vaccines/_coms/clique_pro/group/trends.py
vaccines/_coms/sanic_pro/__init__.py
vaccines/_status/__init__.py
vaccines/_status/status.proc.py
vaccines/_status/monitors/1_mongo_trends_on/monitor_1.py
vaccines/_status/monitors_process/1/monitor_1.py
vaccines/climate/__init__.py
vaccines/climate/mongo/connection_string.py
vaccines/climate/moves/scan_config.py
vaccines/config/scan.py
vaccines/mints/clique.py
vaccines/mints/names.py
vaccines/modules/freight--/save.py
vaccines/modules/moves/mint_to_trends.py
vaccines/modules/moves/trends_to_mint.py
vaccines/modules/moves/save/__init__.py
vaccines/modules/moves/save/modules/zip_and_save_to_gridfs.py
vaccines/modules/moves/trends/extract_to_temp.py
vaccines/modules/moves/trends/find.py
vaccines/modules/moves/trends/forget.py
vaccines/modules/moves/trends/off.py
vaccines/modules/moves/trends/on.py
vaccines/modules/moves/trends/show.py
vaccines/modules/moves/trends/status.py
vaccines/modules/moves/trends/zips/forget.py
vaccines/treasuries/close.py
vaccines/treasuries/create.py
vaccines/treasuries/destroy.py
vaccines/treasuries/names.py
vaccines/treasuries/open.py
vaccines/treasuries/path.py
vaccines/treasuries/search.py
vaccines/treasuries/clique/__init__.py
vaccines-1.0.1.dist-info/METADATA
vaccines-1.0.1.dist-info/WHEEL
vaccines-1.0.1.dist-info/entry_points.txt
vaccines-1.0.1.dist-info/top_level.txt
vaccines-1.0.1.dist-info/RECORD
