Metadata-Version: 2.1
Name: vaccines
Version: 1.0.1
Summary: How to organize remedies.
Keywords: leads,organization
Requires-Dist: volts
Requires-Dist: ships
Requires-Dist: somatic
Requires-Dist: law-dictionary
Requires-Dist: deepmerge
Requires-Dist: pydash
Requires-Dist: pymongo
Requires-Dist: rich
Requires-Dist: tinydb
Requires-Dist: click
